edq_lms_toolkit-1.1.7.dist-info/licenses/LICENSE
lms/__init__.py
lms/py.typed
lms/backend/__init__.py
lms/backend/instance.py
lms/backend/testing.py
lms/backend/blackboard/__init__.py
lms/backend/blackboard/backend.py
lms/backend/blackboard/backend_test.py
lms/backend/blackboard/model.py
lms/backend/canvas/__init__.py
lms/backend/canvas/backend.py
lms/backend/canvas/backend_test.py
lms/backend/canvas/common.py
lms/backend/canvas/model.py
lms/backend/canvas/courses/__init__.py
lms/backend/canvas/courses/list.py
lms/backend/canvas/courses/assignments/__init__.py
lms/backend/canvas/courses/assignments/list.py
lms/backend/canvas/courses/assignments/scores/__init__.py
lms/backend/canvas/courses/assignments/scores/list.py
lms/backend/canvas/courses/assignments/scores/upload.py
lms/backend/canvas/courses/gradebook/__init__.py
lms/backend/canvas/courses/gradebook/fetch.py
lms/backend/canvas/courses/groups/__init__.py
lms/backend/canvas/courses/groups/create.py
lms/backend/canvas/courses/groups/delete.py
lms/backend/canvas/courses/groups/list.py
lms/backend/canvas/courses/groups/memberships/__init__.py
lms/backend/canvas/courses/groups/memberships/add.py
lms/backend/canvas/courses/groups/memberships/list.py
lms/backend/canvas/courses/groups/memberships/subtract.py
lms/backend/canvas/courses/groupsets/__init__.py
lms/backend/canvas/courses/groupsets/create.py
lms/backend/canvas/courses/groupsets/delete.py
lms/backend/canvas/courses/groupsets/list.py
lms/backend/canvas/courses/groupsets/memberships/__init__.py
lms/backend/canvas/courses/groupsets/memberships/list.py
lms/backend/canvas/courses/syllabus/__init__.py
lms/backend/canvas/courses/syllabus/fetch.py
lms/backend/canvas/courses/users/__init__.py
lms/backend/canvas/courses/users/list.py
lms/backend/canvas/courses/users/scores/__init__.py
lms/backend/canvas/courses/users/scores/list.py
lms/backend/moodle/__init__.py
lms/backend/moodle/backend.py
lms/backend/moodle/backend_test.py
lms/backend/testdata/backendtests/__init__.py
edq_lms_toolkit-1.1.7.dist-info/METADATA
edq_lms_toolkit-1.1.7.dist-info/WHEEL
edq_lms_toolkit-1.1.7.dist-info/top_level.txt
edq_lms_toolkit-1.1.7.dist-info/RECORD
