Metadata-Version: 2.4
Name: edq-lms-toolkit
Version: 1.1.7
Summary: A suite of CLI tools and Python library interfacing with Learning Management Systems (LMSs).
Author-email: Eriq Augustine <eriq@edulinq.org>
License: MIT License
Project-URL: Homepage, https://github.com/edulinq/lms-toolkit
Project-URL: Repository, https://github.com/edulinq/lms-toolkit
Keywords: education,lms,canvas,api
Classifier: Intended Audience :: Education
Classifier: License :: OSI Approved :: MIT License
Classifier: Programming Language :: Python :: 3.8
Requires-Python: >=3.8
License-File: LICENSE
Requires-Dist: beautifulsoup4>=4.10.0
Requires-Dist: edq-utils>=0.2.5
Requires-Dist: requests>=2.31.0
Provides-Extra: dev
Requires-Dist: mypy>=1.14.1; extra == "dev"
Requires-Dist: pdoc>=14.7.0; extra == "dev"
Requires-Dist: pylint; extra == "dev"
Requires-Dist: twine; extra == "dev"
Requires-Dist: vermin; extra == "dev"
Dynamic: license-file
